{"ongoing_trials": {}, "hyperparameters": {"space": [{"class_name": "Int", "config": {"name": "input_unit", "default": null, "conditions": [], "min_value": 32, "max_value": 512, "step": 32, "sampling": null}}, {"class_name": "Int", "config": {"name": "n_layers", "default": null, "conditions": [], "min_value": 1, "max_value": 4, "step": 1, "sampling": null}}, {"class_name": "Int", "config": {"name": "lstm_0_units", "default": null, "conditions": [], "min_value": 32, "max_value": 512, "step": 32, "sampling": null}}, {"class_name": "Float", "config": {"name": "Dropout_rate", "default": 0.0, "conditions": [], "min_value": 0.0, "max_value": 0.5, "step": 0.05, "sampling": null}}, {"class_name": "Choice", "config": {"name": "dense_activation", "default": "relu", "conditions": [], "values": ["relu", "sigmoid"], "ordered": false}}, {"class_name": "Int", "config": {"name": "lstm_1_units", "default": null, "conditions": [], "min_value": 32, "max_value": 512, "step": 32, "sampling": null}}, {"class_name": "Int", "config": {"name": "lstm_2_units", "default": null, "conditions": [], "min_value": 32, "max_value": 512, "step": 32, "sampling": null}}], "values": {"input_unit": 32, "n_layers": 1, "lstm_0_units": 32, "Dropout_rate": 0.0, "dense_activation": "relu", "lstm_1_units": 32, "lstm_2_units": 32}}, "seed": 1132, "seed_state": 1198, "tried_so_far": ["54b60f821051ee22037606823870d8d1", "2536f16c0e949ece30a96cf6836e5569", "c244d8971e1391fe34b10569a9495e34", "9f2e6caa173d0ce99ecd1099c22e4a0a", "6805fcdc2648b6f98caa92eb0c4120df", "52cda0727135a051f3933b91fa683ace", "5e088bc85363c0faa77fdfd971ac7b0f", "50356a2814a779736a3b831bf5819d00", "c4d3dd96e3c646a280ba20071e219b96", "69e129c289e6be4682cbff3ef7f48414"]}